{
  "url": "https://api.github.com/repos/alibaba/weex/issues/1674",
  "repository_url": "https://api.github.com/repos/alibaba/weex",
  "labels_url": "https://api.github.com/repos/alibaba/weex/issues/1674/labels{/name}",
  "comments_url": "https://api.github.com/repos/alibaba/weex/issues/1674/comments",
  "events_url": "https://api.github.com/repos/alibaba/weex/issues/1674/events",
  "html_url": "https://github.com/alibaba/weex/issues/1674",
  "id": 190537385,
  "number": 1674,
  "title": "Android WXComponent建议",
  "user": {
    "login": "YanyeZhang",
    "id": 8480050,
    "avatar_url": "https://avatars0.githubusercontent.com/u/8480050?v=3",
    "gravatar_id": "",
    "url": "https://api.github.com/users/YanyeZhang",
    "html_url": "https://github.com/YanyeZhang",
    "followers_url": "https://api.github.com/users/YanyeZhang/followers",
    "following_url": "https://api.github.com/users/YanyeZhang/following{/other_user}",
    "gists_url": "https://api.github.com/users/YanyeZhang/gists{/gist_id}",
    "starred_url": "https://api.github.com/users/YanyeZhang/starred{/owner}{/repo}",
    "subscriptions_url": "https://api.github.com/users/YanyeZhang/subscriptions",
    "organizations_url": "https://api.github.com/users/YanyeZhang/orgs",
    "repos_url": "https://api.github.com/users/YanyeZhang/repos",
    "events_url": "https://api.github.com/users/YanyeZhang/events{/privacy}",
    "received_events_url": "https://api.github.com/users/YanyeZhang/received_events",
    "type": "User",
    "site_admin": false
  },
  "labels": [
    {
      "id": 359381236,
      "url": "https://api.github.com/repos/alibaba/weex/labels/android",
      "name": "android",
      "color": "f9d0c4",
      "default": false
    }
  ],
  "state": "closed",
  "locked": false,
  "assignee": {
    "login": "zshshr",
    "id": 5382962,
    "avatar_url": "https://avatars2.githubusercontent.com/u/5382962?v=3",
    "gravatar_id": "",
    "url": "https://api.github.com/users/zshshr",
    "html_url": "https://github.com/zshshr",
    "followers_url": "https://api.github.com/users/zshshr/followers",
    "following_url": "https://api.github.com/users/zshshr/following{/other_user}",
    "gists_url": "https://api.github.com/users/zshshr/gists{/gist_id}",
    "starred_url": "https://api.github.com/users/zshshr/starred{/owner}{/repo}",
    "subscriptions_url": "https://api.github.com/users/zshshr/subscriptions",
    "organizations_url": "https://api.github.com/users/zshshr/orgs",
    "repos_url": "https://api.github.com/users/zshshr/repos",
    "events_url": "https://api.github.com/users/zshshr/events{/privacy}",
    "received_events_url": "https://api.github.com/users/zshshr/received_events",
    "type": "User",
    "site_admin": false
  },
  "assignees": [
    {
      "login": "zshshr",
      "id": 5382962,
      "avatar_url": "https://avatars2.githubusercontent.com/u/5382962?v=3",
      "gravatar_id": "",
      "url": "https://api.github.com/users/zshshr",
      "html_url": "https://github.com/zshshr",
      "followers_url": "https://api.github.com/users/zshshr/followers",
      "following_url": "https://api.github.com/users/zshshr/following{/other_user}",
      "gists_url": "https://api.github.com/users/zshshr/gists{/gist_id}",
      "starred_url": "https://api.github.com/users/zshshr/starred{/owner}{/repo}",
      "subscriptions_url": "https://api.github.com/users/zshshr/subscriptions",
      "organizations_url": "https://api.github.com/users/zshshr/orgs",
      "repos_url": "https://api.github.com/users/zshshr/repos",
      "events_url": "https://api.github.com/users/zshshr/events{/privacy}",
      "received_events_url": "https://api.github.com/users/zshshr/received_events",
      "type": "User",
      "site_admin": false
    }
  ],
  "milestone": null,
  "comments": [
    {
      "url": "https://api.github.com/repos/alibaba/weex/issues/comments/262137716",
      "html_url": "https://github.com/alibaba/weex/issues/1674#issuecomment-262137716",
      "issue_url": "https://api.github.com/repos/alibaba/weex/issues/1674",
      "id": 262137716,
      "user": {
        "login": "YorkShen",
        "id": 4162544,
        "avatar_url": "https://avatars2.githubusercontent.com/u/4162544?v=3",
        "gravatar_id": "",
        "url": "https://api.github.com/users/YorkShen",
        "html_url": "https://github.com/YorkShen",
        "followers_url": "https://api.github.com/users/YorkShen/followers",
        "following_url": "https://api.github.com/users/YorkShen/following{/other_user}",
        "gists_url": "https://api.github.com/users/YorkShen/gists{/gist_id}",
        "starred_url": "https://api.github.com/users/YorkShen/starred{/owner}{/repo}",
        "subscriptions_url": "https://api.github.com/users/YorkShen/subscriptions",
        "organizations_url": "https://api.github.com/users/YorkShen/orgs",
        "repos_url": "https://api.github.com/users/YorkShen/repos",
        "events_url": "https://api.github.com/users/YorkShen/events{/privacy}",
        "received_events_url": "https://api.github.com/users/YorkShen/received_events",
        "type": "User",
        "site_admin": false
      },
      "created_at": "2016-11-22T03:25:54Z",
      "updated_at": "2016-11-22T03:25:54Z",
      "body": "这段代码的梳理，重构已经完成，目前提交在[long-term-feature](https://github.com/sospartan/weex/blob/tb-dev/android/sdk/src/main/java/com/taobao/weex/ui/component/WXComponent.java#L486)分支，择期与主分支合并。 @YanyeZhang "
    },
    {
      "url": "https://api.github.com/repos/alibaba/weex/issues/comments/262759116",
      "html_url": "https://github.com/alibaba/weex/issues/1674#issuecomment-262759116",
      "issue_url": "https://api.github.com/repos/alibaba/weex/issues/1674",
      "id": 262759116,
      "user": {
        "login": "YanyeZhang",
        "id": 8480050,
        "avatar_url": "https://avatars0.githubusercontent.com/u/8480050?v=3",
        "gravatar_id": "",
        "url": "https://api.github.com/users/YanyeZhang",
        "html_url": "https://github.com/YanyeZhang",
        "followers_url": "https://api.github.com/users/YanyeZhang/followers",
        "following_url": "https://api.github.com/users/YanyeZhang/following{/other_user}",
        "gists_url": "https://api.github.com/users/YanyeZhang/gists{/gist_id}",
        "starred_url": "https://api.github.com/users/YanyeZhang/starred{/owner}{/repo}",
        "subscriptions_url": "https://api.github.com/users/YanyeZhang/subscriptions",
        "organizations_url": "https://api.github.com/users/YanyeZhang/orgs",
        "repos_url": "https://api.github.com/users/YanyeZhang/repos",
        "events_url": "https://api.github.com/users/YanyeZhang/events{/privacy}",
        "received_events_url": "https://api.github.com/users/YanyeZhang/received_events",
        "type": "User",
        "site_admin": false
      },
      "created_at": "2016-11-24T11:52:46Z",
      "updated_at": "2016-11-24T11:52:46Z",
      "body": "@YorkShen  我在以上代码中桥接了自己的下拉刷新，却发现不能够使用 onappear 和on disappear 属性了"
    },
    {
      "url": "https://api.github.com/repos/alibaba/weex/issues/comments/262871327",
      "html_url": "https://github.com/alibaba/weex/issues/1674#issuecomment-262871327",
      "issue_url": "https://api.github.com/repos/alibaba/weex/issues/1674",
      "id": 262871327,
      "user": {
        "login": "YorkShen",
        "id": 4162544,
        "avatar_url": "https://avatars2.githubusercontent.com/u/4162544?v=3",
        "gravatar_id": "",
        "url": "https://api.github.com/users/YorkShen",
        "html_url": "https://github.com/YorkShen",
        "followers_url": "https://api.github.com/users/YorkShen/followers",
        "following_url": "https://api.github.com/users/YorkShen/following{/other_user}",
        "gists_url": "https://api.github.com/users/YorkShen/gists{/gist_id}",
        "starred_url": "https://api.github.com/users/YorkShen/starred{/owner}{/repo}",
        "subscriptions_url": "https://api.github.com/users/YorkShen/subscriptions",
        "organizations_url": "https://api.github.com/users/YorkShen/orgs",
        "repos_url": "https://api.github.com/users/YorkShen/repos",
        "events_url": "https://api.github.com/users/YorkShen/events{/privacy}",
        "received_events_url": "https://api.github.com/users/YorkShen/received_events",
        "type": "User",
        "site_admin": false
      },
      "created_at": "2016-11-25T02:55:31Z",
      "updated_at": "2016-11-25T02:55:31Z",
      "body": "@YanyeZhang 给一下可以复现问题的代码片段"
    },
    {
      "url": "https://api.github.com/repos/alibaba/weex/issues/comments/270364891",
      "html_url": "https://github.com/alibaba/weex/issues/1674#issuecomment-270364891",
      "issue_url": "https://api.github.com/repos/alibaba/weex/issues/1674",
      "id": 270364891,
      "user": {
        "login": "wangweiqi23",
        "id": 6408038,
        "avatar_url": "https://avatars3.githubusercontent.com/u/6408038?v=3",
        "gravatar_id": "",
        "url": "https://api.github.com/users/wangweiqi23",
        "html_url": "https://github.com/wangweiqi23",
        "followers_url": "https://api.github.com/users/wangweiqi23/followers",
        "following_url": "https://api.github.com/users/wangweiqi23/following{/other_user}",
        "gists_url": "https://api.github.com/users/wangweiqi23/gists{/gist_id}",
        "starred_url": "https://api.github.com/users/wangweiqi23/starred{/owner}{/repo}",
        "subscriptions_url": "https://api.github.com/users/wangweiqi23/subscriptions",
        "organizations_url": "https://api.github.com/users/wangweiqi23/orgs",
        "repos_url": "https://api.github.com/users/wangweiqi23/repos",
        "events_url": "https://api.github.com/users/wangweiqi23/events{/privacy}",
        "received_events_url": "https://api.github.com/users/wangweiqi23/received_events",
        "type": "User",
        "site_admin": false
      },
      "created_at": "2017-01-04T12:59:27Z",
      "updated_at": "2017-01-04T12:59:27Z",
      "body": "比如我想改下拉控件 发现只能改源码来实现 weex 很多地方写的太限制@YorkShen "
    },
    {
      "url": "https://api.github.com/repos/alibaba/weex/issues/comments/270827073",
      "html_url": "https://github.com/alibaba/weex/issues/1674#issuecomment-270827073",
      "issue_url": "https://api.github.com/repos/alibaba/weex/issues/1674",
      "id": 270827073,
      "user": {
        "login": "YorkShen",
        "id": 4162544,
        "avatar_url": "https://avatars2.githubusercontent.com/u/4162544?v=3",
        "gravatar_id": "",
        "url": "https://api.github.com/users/YorkShen",
        "html_url": "https://github.com/YorkShen",
        "followers_url": "https://api.github.com/users/YorkShen/followers",
        "following_url": "https://api.github.com/users/YorkShen/following{/other_user}",
        "gists_url": "https://api.github.com/users/YorkShen/gists{/gist_id}",
        "starred_url": "https://api.github.com/users/YorkShen/starred{/owner}{/repo}",
        "subscriptions_url": "https://api.github.com/users/YorkShen/subscriptions",
        "organizations_url": "https://api.github.com/users/YorkShen/orgs",
        "repos_url": "https://api.github.com/users/YorkShen/repos",
        "events_url": "https://api.github.com/users/YorkShen/events{/privacy}",
        "received_events_url": "https://api.github.com/users/YorkShen/received_events",
        "type": "User",
        "site_admin": false
      },
      "created_at": "2017-01-06T04:09:12Z",
      "updated_at": "2017-01-06T04:09:12Z",
      "body": "@wangweiqi23 说你一下你想实现的功能吧"
    }
  ],
  "created_at": "2016-11-20T03:40:23Z",
  "updated_at": "2017-01-06T04:09:12Z",
  "closed_at": "2016-11-22T03:25:54Z",
  "body": "在WXComponent中有以下代码\r\n```java\r\n    if (mParent.getRealView() instanceof ViewPager ) {\r\n//      ViewPager.LayoutParams params = new ViewPager.LayoutParams();\r\n//      params.width = realWidth;\r\n//      params.height = realHeight;\r\n//      mHost.setLayoutParams(params);\r\n    } else if (mParent.getRealView() instanceof BounceRecyclerView && this instanceof WXCell) {\r\n      RecyclerView.LayoutParams params = (RecyclerView.LayoutParams) mHost.getLayoutParams();\r\n      if (params == null)\r\n        params = new RecyclerView.LayoutParams(realWidth,realHeight);\r\n      params.width = realWidth;\r\n      params.height = realHeight;\r\n      params.setMargins(realLeft, 0, realRight, 0);\r\n      mHost.setLayoutParams(params);\r\n    } else if(mParent.getRealView() instanceof BaseBounceView && this instanceof WXBaseRefresh) {\r\n      LinearLayout.LayoutParams params = new LinearLayout.LayoutParams(realWidth,realHeight);\r\n      realTop = (int) (parentPadding.get(Spacing.TOP) - parentBorder.get(Spacing.TOP));\r\n      params.setMargins(realLeft, realTop, realRight, realBottom);\r\n      mHost.setLayoutParams(params);\r\n    } else if (mParent.getRealView() instanceof FrameLayout) {\r\n      FrameLayout.LayoutParams params = new FrameLayout.LayoutParams(realWidth, realHeight);\r\n      params.setMargins(realLeft, realTop, realRight, realBottom);\r\n      mHost.setLayoutParams(params);\r\n    } else if (mParent.getRealView() instanceof LinearLayout) {\r\n      LinearLayout.LayoutParams params = new LinearLayout.LayoutParams(realWidth, realHeight);\r\n      params.setMargins(realLeft, realTop, realRight, realBottom);\r\n      mHost.setLayoutParams(params);\r\n    } else if (mParent.getRealView() instanceof ScrollView) {\r\n      ScrollView.LayoutParams params = new ScrollView.LayoutParams(realWidth, realHeight);\r\n      params.setMargins(realLeft, realTop, realRight, realBottom);\r\n      mHost.setLayoutParams(params);\r\n    }\r\n\r\n```\r\n这段硬编码会导致很多接入的问题。希望把他抽象出来。"
}
