{
  "url": "https://api.github.com/repos/alibaba/weex/issues/1929",
  "repository_url": "https://api.github.com/repos/alibaba/weex",
  "labels_url": "https://api.github.com/repos/alibaba/weex/issues/1929/labels{/name}",
  "comments_url": "https://api.github.com/repos/alibaba/weex/issues/1929/comments",
  "events_url": "https://api.github.com/repos/alibaba/weex/issues/1929/events",
  "html_url": "https://github.com/alibaba/weex/issues/1929",
  "id": 196148438,
  "number": 1929,
  "title": "Simple Android Wrapper",
  "user": {
    "login": "rizkyramadhan",
    "id": 126301,
    "avatar_url": "https://avatars2.githubusercontent.com/u/126301?v=3",
    "gravatar_id": "",
    "url": "https://api.github.com/users/rizkyramadhan",
    "html_url": "https://github.com/rizkyramadhan",
    "followers_url": "https://api.github.com/users/rizkyramadhan/followers",
    "following_url": "https://api.github.com/users/rizkyramadhan/following{/other_user}",
    "gists_url": "https://api.github.com/users/rizkyramadhan/gists{/gist_id}",
    "starred_url": "https://api.github.com/users/rizkyramadhan/starred{/owner}{/repo}",
    "subscriptions_url": "https://api.github.com/users/rizkyramadhan/subscriptions",
    "organizations_url": "https://api.github.com/users/rizkyramadhan/orgs",
    "repos_url": "https://api.github.com/users/rizkyramadhan/repos",
    "events_url": "https://api.github.com/users/rizkyramadhan/events{/privacy}",
    "received_events_url": "https://api.github.com/users/rizkyramadhan/received_events",
    "type": "User",
    "site_admin": false
  },
  "labels": [],
  "state": "closed",
  "locked": false,
  "assignee": null,
  "assignees": [],
  "milestone": null,
  "comments": [
    {
      "url": "https://api.github.com/repos/alibaba/weex/issues/comments/267749645",
      "html_url": "https://github.com/alibaba/weex/issues/1929#issuecomment-267749645",
      "issue_url": "https://api.github.com/repos/alibaba/weex/issues/1929",
      "id": 267749645,
      "user": {
        "login": "Jinjiang",
        "id": 206848,
        "avatar_url": "https://avatars2.githubusercontent.com/u/206848?v=3",
        "gravatar_id": "",
        "url": "https://api.github.com/users/Jinjiang",
        "html_url": "https://github.com/Jinjiang",
        "followers_url": "https://api.github.com/users/Jinjiang/followers",
        "following_url": "https://api.github.com/users/Jinjiang/following{/other_user}",
        "gists_url": "https://api.github.com/users/Jinjiang/gists{/gist_id}",
        "starred_url": "https://api.github.com/users/Jinjiang/starred{/owner}{/repo}",
        "subscriptions_url": "https://api.github.com/users/Jinjiang/subscriptions",
        "organizations_url": "https://api.github.com/users/Jinjiang/orgs",
        "repos_url": "https://api.github.com/users/Jinjiang/repos",
        "events_url": "https://api.github.com/users/Jinjiang/events{/privacy}",
        "received_events_url": "https://api.github.com/users/Jinjiang/received_events",
        "type": "User",
        "site_admin": false
      },
      "created_at": "2016-12-17T08:09:29Z",
      "updated_at": "2016-12-17T08:09:29Z",
      "body": "We have a Weex Playground App in our download web page.\r\n\r\nhttp://alibaba.github.io/weex/download.html\r\n\r\nYou can write some code through http://dotwe.org/ just like codepen. And then you can easily preview the render effect by scan the qrcode with Weex Playground App.\r\n\r\nAnd of cource you can also make a server by your own using `weex-loader`\r\n\r\nThanks."
    },
    {
      "url": "https://api.github.com/repos/alibaba/weex/issues/comments/267749673",
      "html_url": "https://github.com/alibaba/weex/issues/1929#issuecomment-267749673",
      "issue_url": "https://api.github.com/repos/alibaba/weex/issues/1929",
      "id": 267749673,
      "user": {
        "login": "Jinjiang",
        "id": 206848,
        "avatar_url": "https://avatars2.githubusercontent.com/u/206848?v=3",
        "gravatar_id": "",
        "url": "https://api.github.com/users/Jinjiang",
        "html_url": "https://github.com/Jinjiang",
        "followers_url": "https://api.github.com/users/Jinjiang/followers",
        "following_url": "https://api.github.com/users/Jinjiang/following{/other_user}",
        "gists_url": "https://api.github.com/users/Jinjiang/gists{/gist_id}",
        "starred_url": "https://api.github.com/users/Jinjiang/starred{/owner}{/repo}",
        "subscriptions_url": "https://api.github.com/users/Jinjiang/subscriptions",
        "organizations_url": "https://api.github.com/users/Jinjiang/orgs",
        "repos_url": "https://api.github.com/users/Jinjiang/repos",
        "events_url": "https://api.github.com/users/Jinjiang/events{/privacy}",
        "received_events_url": "https://api.github.com/users/Jinjiang/received_events",
        "type": "User",
        "site_admin": false
      },
      "created_at": "2016-12-17T08:10:06Z",
      "updated_at": "2016-12-17T08:10:06Z",
      "body": "btw the source code of Weex Playground App is in `./android/playground` and `./ios/playground`"
    }
  ],
  "created_at": "2016-12-16T20:32:45Z",
  "updated_at": "2016-12-23T23:42:15Z",
  "closed_at": "2016-12-23T23:42:15Z",
  "body": "Is there any pre-made android wrapper apk?, so that I just need to put some configuration file to load .we from my server, change the icon and app name, and then ship it. \r\n\r\nCurrent playground apk is great for showcasing weex, but it cannot start with my .we. \r\n\r\nI think it will greatly simplify weex development / deployment.\r\n\r\n \r\n",
  "closed_by": {
    "login": "Jinjiang",
    "id": 206848,
    "avatar_url": "https://avatars2.githubusercontent.com/u/206848?v=3",
    "gravatar_id": "",
    "url": "https://api.github.com/users/Jinjiang",
    "html_url": "https://github.com/Jinjiang",
    "followers_url": "https://api.github.com/users/Jinjiang/followers",
    "following_url": "https://api.github.com/users/Jinjiang/following{/other_user}",
    "gists_url": "https://api.github.com/users/Jinjiang/gists{/gist_id}",
    "starred_url": "https://api.github.com/users/Jinjiang/starred{/owner}{/repo}",
    "subscriptions_url": "https://api.github.com/users/Jinjiang/subscriptions",
    "organizations_url": "https://api.github.com/users/Jinjiang/orgs",
    "repos_url": "https://api.github.com/users/Jinjiang/repos",
    "events_url": "https://api.github.com/users/Jinjiang/events{/privacy}",
    "received_events_url": "https://api.github.com/users/Jinjiang/received_events",
    "type": "User",
    "site_admin": false
  }
}
