{
  "url": "https://api.github.com/repos/alibaba/weex/issues/2853",
  "repository_url": "https://api.github.com/repos/alibaba/weex",
  "labels_url": "https://api.github.com/repos/alibaba/weex/issues/2853/labels{/name}",
  "comments_url": "https://api.github.com/repos/alibaba/weex/issues/2853/comments",
  "events_url": "https://api.github.com/repos/alibaba/weex/issues/2853/events",
  "html_url": "https://github.com/alibaba/weex/issues/2853",
  "id": 211958152,
  "number": 2853,
  "title": "装了toolkit,没有devtool",
  "user": {
    "login": "wxxcarl",
    "id": 3860334,
    "avatar_url": "https://avatars0.githubusercontent.com/u/3860334?v=3",
    "gravatar_id": "",
    "url": "https://api.github.com/users/wxxcarl",
    "html_url": "https://github.com/wxxcarl",
    "followers_url": "https://api.github.com/users/wxxcarl/followers",
    "following_url": "https://api.github.com/users/wxxcarl/following{/other_user}",
    "gists_url": "https://api.github.com/users/wxxcarl/gists{/gist_id}",
    "starred_url": "https://api.github.com/users/wxxcarl/starred{/owner}{/repo}",
    "subscriptions_url": "https://api.github.com/users/wxxcarl/subscriptions",
    "organizations_url": "https://api.github.com/users/wxxcarl/orgs",
    "repos_url": "https://api.github.com/users/wxxcarl/repos",
    "events_url": "https://api.github.com/users/wxxcarl/events{/privacy}",
    "received_events_url": "https://api.github.com/users/wxxcarl/received_events",
    "type": "User",
    "site_admin": false
  },
  "labels": [],
  "state": "open",
  "locked": false,
  "assignee": null,
  "assignees": [],
  "milestone": null,
  "comments": [
    {
      "url": "https://api.github.com/repos/alibaba/weex/issues/comments/284961798",
      "html_url": "https://github.com/alibaba/weex/issues/2853#issuecomment-284961798",
      "issue_url": "https://api.github.com/repos/alibaba/weex/issues/2853",
      "id": 284961798,
      "user": {
        "login": "JackPu",
        "id": 4744967,
        "avatar_url": "https://avatars3.githubusercontent.com/u/4744967?v=3",
        "gravatar_id": "",
        "url": "https://api.github.com/users/JackPu",
        "html_url": "https://github.com/JackPu",
        "followers_url": "https://api.github.com/users/JackPu/followers",
        "following_url": "https://api.github.com/users/JackPu/following{/other_user}",
        "gists_url": "https://api.github.com/users/JackPu/gists{/gist_id}",
        "starred_url": "https://api.github.com/users/JackPu/starred{/owner}{/repo}",
        "subscriptions_url": "https://api.github.com/users/JackPu/subscriptions",
        "organizations_url": "https://api.github.com/users/JackPu/orgs",
        "repos_url": "https://api.github.com/users/JackPu/repos",
        "events_url": "https://api.github.com/users/JackPu/events{/privacy}",
        "received_events_url": "https://api.github.com/users/JackPu/received_events",
        "type": "User",
        "site_admin": false
      },
      "created_at": "2017-03-08T06:47:43Z",
      "updated_at": "2017-03-08T06:47:43Z",
      "body": "@wxxcarl  你能贴下你的错误信息，如果是权限问题你改下你当前用户目录的权限."
    }
  ],
  "created_at": "2017-03-05T15:00:29Z",
  "updated_at": "2017-03-08T06:47:43Z",
  "closed_at": null,
  "body": "weex-toolkit已经安装了，不是说包括devtool的吗？当我运行 weex debug的时候，提示\r\n\r\n`This command need to install weex-devtool. Install now? (Y/n) `\r\n\r\n我确认安装，结果权限不对，我要用sudo装的，这种情况怎么解决？？另外我试着重新sudo npm install weex-devtool -g，运行weex-debug还是一样的提示，什么鬼？？！！！",
  "closed_by": null
}
