{
  "url": "https://api.github.com/repos/alibaba/weex/issues/1841",
  "repository_url": "https://api.github.com/repos/alibaba/weex",
  "labels_url": "https://api.github.com/repos/alibaba/weex/issues/1841/labels{/name}",
  "comments_url": "https://api.github.com/repos/alibaba/weex/issues/1841/comments",
  "events_url": "https://api.github.com/repos/alibaba/weex/issues/1841/events",
  "html_url": "https://github.com/alibaba/weex/pull/1841",
  "id": 194290694,
  "number": 1841,
  "title": "+ [example] add picker example for playgound",
  "user": {
    "login": "kfeagle",
    "id": 11485145,
    "avatar_url": "https://avatars0.githubusercontent.com/u/11485145?v=3",
    "gravatar_id": "",
    "url": "https://api.github.com/users/kfeagle",
    "html_url": "https://github.com/kfeagle",
    "followers_url": "https://api.github.com/users/kfeagle/followers",
    "following_url": "https://api.github.com/users/kfeagle/following{/other_user}",
    "gists_url": "https://api.github.com/users/kfeagle/gists{/gist_id}",
    "starred_url": "https://api.github.com/users/kfeagle/starred{/owner}{/repo}",
    "subscriptions_url": "https://api.github.com/users/kfeagle/subscriptions",
    "organizations_url": "https://api.github.com/users/kfeagle/orgs",
    "repos_url": "https://api.github.com/users/kfeagle/repos",
    "events_url": "https://api.github.com/users/kfeagle/events{/privacy}",
    "received_events_url": "https://api.github.com/users/kfeagle/received_events",
    "type": "User",
    "site_admin": false
  },
  "labels": [],
  "state": "closed",
  "locked": false,
  "assignee": null,
  "assignees": [],
  "milestone": null,
  "comments": [],
  "created_at": "2016-12-08T09:51:19Z",
  "updated_at": "2016-12-08T09:51:31Z",
  "closed_at": "2016-12-08T09:51:31Z",
  "pull_request": {
    "url": "https://api.github.com/repos/alibaba/weex/pulls/1841",
    "html_url": "https://github.com/alibaba/weex/pull/1841",
    "diff_url": "https://github.com/alibaba/weex/pull/1841.diff",
    "patch_url": "https://github.com/alibaba/weex/pull/1841.patch"
  },
  "body": "add picker example for playgound"
}
