{
  "url": "https://api.github.com/repos/alibaba/weex/issues/738",
  "repository_url": "https://api.github.com/repos/alibaba/weex",
  "labels_url": "https://api.github.com/repos/alibaba/weex/issues/738/labels{/name}",
  "comments_url": "https://api.github.com/repos/alibaba/weex/issues/738/comments",
  "events_url": "https://api.github.com/repos/alibaba/weex/issues/738/events",
  "html_url": "https://github.com/alibaba/weex/pull/738",
  "id": 164227657,
  "number": 738,
  "title": "* [ios] change list document for 0.6.0 features.",
  "user": {
    "login": "cxfeng1",
    "id": 1625893,
    "avatar_url": "https://avatars2.githubusercontent.com/u/1625893?v=3",
    "gravatar_id": "",
    "url": "https://api.github.com/users/cxfeng1",
    "html_url": "https://github.com/cxfeng1",
    "followers_url": "https://api.github.com/users/cxfeng1/followers",
    "following_url": "https://api.github.com/users/cxfeng1/following{/other_user}",
    "gists_url": "https://api.github.com/users/cxfeng1/gists{/gist_id}",
    "starred_url": "https://api.github.com/users/cxfeng1/starred{/owner}{/repo}",
    "subscriptions_url": "https://api.github.com/users/cxfeng1/subscriptions",
    "organizations_url": "https://api.github.com/users/cxfeng1/orgs",
    "repos_url": "https://api.github.com/users/cxfeng1/repos",
    "events_url": "https://api.github.com/users/cxfeng1/events{/privacy}",
    "received_events_url": "https://api.github.com/users/cxfeng1/received_events",
    "type": "User",
    "site_admin": false
  },
  "labels": [],
  "state": "closed",
  "locked": false,
  "assignee": {
    "login": "luics",
    "id": 1018815,
    "avatar_url": "https://avatars0.githubusercontent.com/u/1018815?v=3",
    "gravatar_id": "",
    "url": "https://api.github.com/users/luics",
    "html_url": "https://github.com/luics",
    "followers_url": "https://api.github.com/users/luics/followers",
    "following_url": "https://api.github.com/users/luics/following{/other_user}",
    "gists_url": "https://api.github.com/users/luics/gists{/gist_id}",
    "starred_url": "https://api.github.com/users/luics/starred{/owner}{/repo}",
    "subscriptions_url": "https://api.github.com/users/luics/subscriptions",
    "organizations_url": "https://api.github.com/users/luics/orgs",
    "repos_url": "https://api.github.com/users/luics/repos",
    "events_url": "https://api.github.com/users/luics/events{/privacy}",
    "received_events_url": "https://api.github.com/users/luics/received_events",
    "type": "User",
    "site_admin": false
  },
  "assignees": [
    {
      "login": "luics",
      "id": 1018815,
      "avatar_url": "https://avatars0.githubusercontent.com/u/1018815?v=3",
      "gravatar_id": "",
      "url": "https://api.github.com/users/luics",
      "html_url": "https://github.com/luics",
      "followers_url": "https://api.github.com/users/luics/followers",
      "following_url": "https://api.github.com/users/luics/following{/other_user}",
      "gists_url": "https://api.github.com/users/luics/gists{/gist_id}",
      "starred_url": "https://api.github.com/users/luics/starred{/owner}{/repo}",
      "subscriptions_url": "https://api.github.com/users/luics/subscriptions",
      "organizations_url": "https://api.github.com/users/luics/orgs",
      "repos_url": "https://api.github.com/users/luics/repos",
      "events_url": "https://api.github.com/users/luics/events{/privacy}",
      "received_events_url": "https://api.github.com/users/luics/received_events",
      "type": "User",
      "site_admin": false
    }
  ],
  "milestone": null,
  "comments": [],
  "created_at": "2016-07-07T04:32:12Z",
  "updated_at": "2016-07-07T06:44:16Z",
  "closed_at": "2016-07-07T06:44:16Z",
  "pull_request": {
    "url": "https://api.github.com/repos/alibaba/weex/pulls/738",
    "html_url": "https://github.com/alibaba/weex/pull/738",
    "diff_url": "https://github.com/alibaba/weex/pull/738.diff",
    "patch_url": "https://github.com/alibaba/weex/pull/738.patch"
  },
  "body": "",
  "closed_by": {
    "login": "luics",
    "id": 1018815,
    "avatar_url": "https://avatars0.githubusercontent.com/u/1018815?v=3",
    "gravatar_id": "",
    "url": "https://api.github.com/users/luics",
    "html_url": "https://github.com/luics",
    "followers_url": "https://api.github.com/users/luics/followers",
    "following_url": "https://api.github.com/users/luics/following{/other_user}",
    "gists_url": "https://api.github.com/users/luics/gists{/gist_id}",
    "starred_url": "https://api.github.com/users/luics/starred{/owner}{/repo}",
    "subscriptions_url": "https://api.github.com/users/luics/subscriptions",
    "organizations_url": "https://api.github.com/users/luics/orgs",
    "repos_url": "https://api.github.com/users/luics/repos",
    "events_url": "https://api.github.com/users/luics/events{/privacy}",
    "received_events_url": "https://api.github.com/users/luics/received_events",
    "type": "User",
    "site_admin": false
  }
}
