{
  "url": "https://api.github.com/repos/alibaba/weex/issues/973",
  "repository_url": "https://api.github.com/repos/alibaba/weex",
  "labels_url": "https://api.github.com/repos/alibaba/weex/issues/973/labels{/name}",
  "comments_url": "https://api.github.com/repos/alibaba/weex/issues/973/comments",
  "events_url": "https://api.github.com/repos/alibaba/weex/issues/973/events",
  "html_url": "https://github.com/alibaba/weex/pull/973",
  "id": 170343707,
  "number": 973,
  "title": "Html5 feature refactor",
  "user": {
    "login": "MrRaindrop",
    "id": 1545874,
    "avatar_url": "https://avatars3.githubusercontent.com/u/1545874?v=3",
    "gravatar_id": "",
    "url": "https://api.github.com/users/MrRaindrop",
    "html_url": "https://github.com/MrRaindrop",
    "followers_url": "https://api.github.com/users/MrRaindrop/followers",
    "following_url": "https://api.github.com/users/MrRaindrop/following{/other_user}",
    "gists_url": "https://api.github.com/users/MrRaindrop/gists{/gist_id}",
    "starred_url": "https://api.github.com/users/MrRaindrop/starred{/owner}{/repo}",
    "subscriptions_url": "https://api.github.com/users/MrRaindrop/subscriptions",
    "organizations_url": "https://api.github.com/users/MrRaindrop/orgs",
    "repos_url": "https://api.github.com/users/MrRaindrop/repos",
    "events_url": "https://api.github.com/users/MrRaindrop/events{/privacy}",
    "received_events_url": "https://api.github.com/users/MrRaindrop/received_events",
    "type": "User",
    "site_admin": false
  },
  "labels": [
    {
      "id": 359381235,
      "url": "https://api.github.com/repos/alibaba/weex/labels/html5",
      "name": "html5",
      "color": "f9d0c4",
      "default": false
    },
    {
      "id": 359381537,
      "url": "https://api.github.com/repos/alibaba/weex/labels/js%20runtime",
      "name": "js runtime",
      "color": "f9d0c4",
      "default": false
    }
  ],
  "state": "closed",
  "locked": false,
  "assignee": {
    "login": "Jinjiang",
    "id": 206848,
    "avatar_url": "https://avatars2.githubusercontent.com/u/206848?v=3",
    "gravatar_id": "",
    "url": "https://api.github.com/users/Jinjiang",
    "html_url": "https://github.com/Jinjiang",
    "followers_url": "https://api.github.com/users/Jinjiang/followers",
    "following_url": "https://api.github.com/users/Jinjiang/following{/other_user}",
    "gists_url": "https://api.github.com/users/Jinjiang/gists{/gist_id}",
    "starred_url": "https://api.github.com/users/Jinjiang/starred{/owner}{/repo}",
    "subscriptions_url": "https://api.github.com/users/Jinjiang/subscriptions",
    "organizations_url": "https://api.github.com/users/Jinjiang/orgs",
    "repos_url": "https://api.github.com/users/Jinjiang/repos",
    "events_url": "https://api.github.com/users/Jinjiang/events{/privacy}",
    "received_events_url": "https://api.github.com/users/Jinjiang/received_events",
    "type": "User",
    "site_admin": false
  },
  "assignees": [
    {
      "login": "Jinjiang",
      "id": 206848,
      "avatar_url": "https://avatars2.githubusercontent.com/u/206848?v=3",
      "gravatar_id": "",
      "url": "https://api.github.com/users/Jinjiang",
      "html_url": "https://github.com/Jinjiang",
      "followers_url": "https://api.github.com/users/Jinjiang/followers",
      "following_url": "https://api.github.com/users/Jinjiang/following{/other_user}",
      "gists_url": "https://api.github.com/users/Jinjiang/gists{/gist_id}",
      "starred_url": "https://api.github.com/users/Jinjiang/starred{/owner}{/repo}",
      "subscriptions_url": "https://api.github.com/users/Jinjiang/subscriptions",
      "organizations_url": "https://api.github.com/users/Jinjiang/orgs",
      "repos_url": "https://api.github.com/users/Jinjiang/repos",
      "events_url": "https://api.github.com/users/Jinjiang/events{/privacy}",
      "received_events_url": "https://api.github.com/users/Jinjiang/received_events",
      "type": "User",
      "site_admin": false
    },
    {
      "login": "gurisxie",
      "id": 7436932,
      "avatar_url": "https://avatars2.githubusercontent.com/u/7436932?v=3",
      "gravatar_id": "",
      "url": "https://api.github.com/users/gurisxie",
      "html_url": "https://github.com/gurisxie",
      "followers_url": "https://api.github.com/users/gurisxie/followers",
      "following_url": "https://api.github.com/users/gurisxie/following{/other_user}",
      "gists_url": "https://api.github.com/users/gurisxie/gists{/gist_id}",
      "starred_url": "https://api.github.com/users/gurisxie/starred{/owner}{/repo}",
      "subscriptions_url": "https://api.github.com/users/gurisxie/subscriptions",
      "organizations_url": "https://api.github.com/users/gurisxie/orgs",
      "repos_url": "https://api.github.com/users/gurisxie/repos",
      "events_url": "https://api.github.com/users/gurisxie/events{/privacy}",
      "received_events_url": "https://api.github.com/users/gurisxie/received_events",
      "type": "User",
      "site_admin": false
    }
  ],
  "milestone": null,
  "comments": [],
  "created_at": "2016-08-10T07:03:02Z",
  "updated_at": "2016-08-11T08:48:48Z",
  "closed_at": "2016-08-11T08:48:48Z",
  "pull_request": {
    "url": "https://api.github.com/repos/alibaba/weex/pulls/973",
    "html_url": "https://github.com/alibaba/weex/pull/973",
    "diff_url": "https://github.com/alibaba/weex/pull/973.diff",
    "patch_url": "https://github.com/alibaba/weex/pull/973.patch"
  },
  "body": "**html5 renderer**\n- vdom-render refactoring, using ComponentManager as a Listener to the vdom Document.\n- rearrange the architecture of renderer's code and files.\n- registering and installing of the components and api modules are no longer relying on the requiring code of weex.\n\n**jsfm**\n- `createInstance` in jsfm return a app instance rather than undefined or error.\n- remove console reimplementation，using debug flag in url to toggle console.debug.\n- pass a Listener to the Document constructor to specify which listener the document use.\n- separate `ctrl.js` into `init.js` and `misc.js`. The `misc` contains：\n  - `updateActions`\n  - `destroy`\n  - `getRootElement`\n  - `fireEvent`\n  - `callback`\n  - `refreshData`\n- separate `default/index.js` into `create`, `map`, `register`, `bridge`, `life` and `misc` in the path `default/static`. The including methods in the above files excludes `create` are:\n  - `init`\n  - `refreshInstance`\n  - `destroyInstance`\n  - `registerComponents`\n  - `registerModules`\n  - `registerMethods`\n  - `getRoot`\n  - `receiveTasks`\n- `init` method of `runtime` add arguments of frameworks and listener\n"
}
